{
    "version": "1.0",
    "name": "Corporate",
    "description": "Template corporate professionnel avec en-tête coloré",
    "category": "business",
    "features": [
        "Professionnel",
        "Corporate",
        "Entreprise"
    ],
    "canvasWidth": 300,
    "canvasHeight": 200,
    "elements": [
        {
            "id": "header-background",
            "type": "rectangle",
            "x": 0,
            "y": 0,
            "width": 300,
            "height": 12,
            "properties": {
                "fillColor": "#28a745",
                "strokeWidth": 0
            }
        },
        {
            "id": "logo-circle",
            "type": "circle",
            "x": 15,
            "y": 6,
            "width": 6,
            "height": 6,
            "properties": {
                "fillColor": "#ffffff",
                "strokeWidth": 0,
                "opacity": 0.8
            }
        },
        {
            "id": "logo-text",
            "type": "text",
            "x": 15,
            "y": 4,
            "width": 6,
            "height": 6,
            "properties": {
                "text": "✓",
                "fontSize": 6,
                "fontFamily": "Arial",
                "fontWeight": "bold",
                "color": "#28a745",
                "textAlign": "center"
            }
        },
        {
            "id": "company-name",
            "type": "text",
            "x": 35,
            "y": 8,
            "width": 200,
            "height": 8,
            "properties": {
                "text": "{{company_name}}",
                "fontSize": 6,
                "fontFamily": "Arial",
                "fontWeight": "bold",
                "color": "#28a745",
                "textAlign": "left"
            }
        },
        {
            "id": "company-address",
            "type": "text",
            "x": 10,
            "y": 32,
            "width": 200,
            "height": 5,
            "properties": {
                "text": "{{company_address}}",
                "fontSize": 5,
                "fontFamily": "Arial",
                "color": "#6c757d",
                "textAlign": "left"
            }
        },
        {
            "id": "company-details",
            "type": "text",
            "x": 10,
            "y": 39,
            "width": 200,
            "height": 5,
            "properties": {
                "text": "SIRET: {{company_siret}} • TVA: {{company_vat}}",
                "fontSize": 5,
                "fontFamily": "Arial",
                "color": "#6c757d",
                "textAlign": "left"
            }
        },
        {
            "id": "client-label",
            "type": "text",
            "x": 10,
            "y": 50,
            "width": 100,
            "height": 5,
            "properties": {
                "text": "CLIENT:",
                "fontSize": 5,
                "fontFamily": "Arial",
                "fontWeight": "bold",
                "color": "#28a745",
                "textAlign": "left"
            }
        },
        {
            "id": "client-name",
            "type": "text",
            "x": 10,
            "y": 56,
            "width": 100,
            "height": 5,
            "properties": {
                "text": "{{customer_name}}",
                "fontSize": 5,
                "fontFamily": "Arial",
                "color": "#212529",
                "textAlign": "left"
            }
        },
        {
            "id": "client-address",
            "type": "text",
            "x": 10,
            "y": 61,
            "width": 100,
            "height": 5,
            "properties": {
                "text": "{{customer_address}}",
                "fontSize": 5,
                "fontFamily": "Arial",
                "color": "#212529",
                "textAlign": "left"
            }
        },
        {
            "id": "order-number",
            "type": "text",
            "x": 180,
            "y": 50,
            "width": 110,
            "height": 5,
            "properties": {
                "text": "N° CMM-XXXX-XXXX",
                "fontSize": 5,
                "fontFamily": "Arial",
                "fontWeight": "bold",
                "color": "#28a745",
                "textAlign": "end"
            }
        },
        {
            "id": "order-date",
            "type": "text",
            "x": 180,
            "y": 56,
            "width": 110,
            "height": 5,
            "properties": {
                "text": "Date: {{order_date}}",
                "fontSize": 5,
                "fontFamily": "Arial",
                "color": "#212529",
                "textAlign": "end"
            }
        },
        {
            "id": "client-phone",
            "type": "text",
            "x": 180,
            "y": 61,
            "width": 110,
            "height": 5,
            "properties": {
                "text": "{{customer_phone}}",
                "fontSize": 5,
                "fontFamily": "Arial",
                "color": "#212529",
                "textAlign": "end"
            }
        },
        {
            "id": "table-header-bg",
            "type": "rectangle",
            "x": 10,
            "y": 68,
            "width": 280,
            "height": 9,
            "properties": {
                "fillColor": "#28a745",
                "strokeWidth": 0
            }
        },
        {
            "id": "table-header",
            "type": "text",
            "x": 15,
            "y": 74,
            "width": 270,
            "height": 5,
            "properties": {
                "text": "Produit\tQté\tPrix\tTotal",
                "fontSize": 5,
                "fontFamily": "Arial",
                "fontWeight": "bold",
                "color": "#ffffff",
                "textAlign": "left"
            }
        },
        {
            "id": "items-table",
            "type": "product_table",
            "x": 10,
            "y": 77,
            "width": 280,
            "height": 20,
            "properties": {
                "showHeaders": false,
                "showBorders": true,
                "showAlternatingRows": true,
                "showSku": false,
                "showDescription": false,
                "showQuantity": true,
                "fontSize": 5,
                "fontFamily": "Arial",
                "textColor": "#212529",
                "headerBackgroundColor": "#28a745",
                "headerTextColor": "#ffffff",
                "alternateRowColor": "#f8f9fa",
                "borderColor": "#ecf0f1",
                "borderWidth": 1,
                "textAlign": "left"
            }
        },
        {
            "id": "totals-separator",
            "type": "line",
            "x": 160,
            "y": 100,
            "width": 130,
            "height": 0,
            "properties": {
                "strokeColor": "#e0e0e0",
                "strokeWidth": 0.5
            }
        },
        {
            "id": "subtotal-label",
            "type": "text",
            "x": 200,
            "y": 110,
            "width": 60,
            "height": 5,
            "properties": {
                "text": "Sous-total:",
                "fontSize": 5,
                "fontFamily": "Arial",
                "color": "#6c757d",
                "textAlign": "left"
            }
        },
        {
            "id": "subtotal-value",
            "type": "text",
            "x": 285,
            "y": 110,
            "width": 20,
            "height": 5,
            "properties": {
                "text": "{{subtotal}}",
                "fontSize": 5,
                "fontFamily": "Arial",
                "fontWeight": "bold",
                "color": "#28a745",
                "textAlign": "end"
            }
        },
        {
            "id": "discount-label",
            "type": "text",
            "x": 200,
            "y": 118,
            "width": 60,
            "height": 5,
            "properties": {
                "text": "Coupon:",
                "fontSize": 5,
                "fontFamily": "Arial",
                "color": "#6c757d",
                "textAlign": "left"
            }
        },
        {
            "id": "discount-value",
            "type": "text",
            "x": 285,
            "y": 118,
            "width": 20,
            "height": 5,
            "properties": {
                "text": "-{{discount}}",
                "fontSize": 5,
                "fontFamily": "Arial",
                "fontWeight": "bold",
                "color": "#28a745",
                "textAlign": "end"
            }
        },
        {
            "id": "total-background",
            "type": "rectangle",
            "x": 160,
            "y": 122,
            "width": 125,
            "height": 8,
            "properties": {
                "fillColor": "#28a745",
                "strokeWidth": 0,
                "borderRadius": 4,
                "opacity": 0.1
            }
        },
        {
            "id": "total-label",
            "type": "text",
            "x": 160,
            "y": 129,
            "width": 50,
            "height": 5,
            "properties": {
                "text": "TOTAL:",
                "fontSize": 5,
                "fontFamily": "Arial",
                "fontWeight": "bold",
                "color": "#28a745",
                "textAlign": "right"
            }
        },
        {
            "id": "total-value",
            "type": "text",
            "x": 285,
            "y": 129,
            "width": 20,
            "height": 5,
            "properties": {
                "text": "{{total}}",
                "fontSize": 5,
                "fontFamily": "Arial",
                "fontWeight": "bold",
                "color": "#28a745",
                "textAlign": "right"
            }
        },
        {
            "id": "footer-mentions",
            "type": "mentions",
            "x": 67,
            "y": 145,
            "width": 285,
            "height": 5,
            "properties": {
                "showEmail": true,
                "showPhone": false,
                "showSiret": false,
                "showVat": false,
                "separator": " • ",
                "fontSize": 5,
                "fontFamily": "Arial",
                "textColor": "#adb5bd",
                "textAlign": "center",
                "lineHeight": 1.4
            }
        }
    ],
    "metadata": {
        "name": "Corporate",
        "description": "Template corporate professionnel avec en-tête coloré",
        "category": "business",
        "preview": "corporate-preview.png"
    }
}